ics_to_todoist-24.12.dist-info/METADATA
ics_to_todoist-24.12.dist-info/WHEEL
ics_to_todoist-24.12.dist-info/entry_points.txt
ics_to_todoist-24.12.dist-info/licenses/LICENSE.md
ics_to_todoist/__init__.py
ics_to_todoist/__main__.py
ics_to_todoist/models/__init__.py
ics_to_todoist/models/configuration.py
ics_to_todoist/models/event.py
ics_to_todoist/models/reminder_time.py
ics_to_todoist/todoist_helper.py
ics_to_todoist-24.12.dist-info/RECORD
