Metadata-Version: 2.1
Name: ics-to-todoist
Version: 24.12
Summary: A command line tool to convert entries from an .ics file to tasks in Todoist.
Keywords: ics,todoist
Author: Gabor Schulz
License: MIT
Classifier: Development Status :: 3 - Alpha
Classifier: Environment :: Console
Classifier: License :: OSI Approved :: MIT License
Classifier: Natural Language :: English
Classifier: Operating System :: OS Independent
Classifier: Programming Language :: Python
Classifier: Programming Language :: Python :: 3
Classifier: Programming Language :: Python :: 3 :: Only
Classifier: Programming Language :: Python :: 3.12
Classifier: Programming Language :: Python :: 3.13
Classifier: Topic :: Utilities
Project-URL: Homepage, https://gaborschulz.github.io/ics-to-todoist/
Project-URL: Repository, https://github.com/gaborschulz/ics-to-todoist
Requires-Python: >=3.12
Requires-Dist: typer[all]>=0.12.5
Requires-Dist: ics>=0.7.2
Requires-Dist: python-dotenv>=1.0.1
Requires-Dist: pydantic>=2.8.2
Requires-Dist: pydantic-settings>=2.4.0
Requires-Dist: httpx>=0.27.2
Requires-Dist: todoist-api-python>=2.1.7
Provides-Extra: docs
Requires-Dist: mkdocs>=1.6.1; extra == "docs"
Requires-Dist: mkdocs-material>=9.5.33; extra == "docs"
